[
  {
    "title":"section 1",
    "submenu": [
      {
        "title":"App Setup",
        "file":"app_setup"
      },
      {
        "title":"file 3",
        "file":"file3"
      }
    ]
  },
  {
    "title":"Endpoints",
    "submenu": [
      {
        "title":"file 4",
        "file":"file4"
      },
      {
        "title":"file 5",
        "file":"file5"
      },
      {
        "title":"file 6",
        "file":"file6"
      }
    ]
  },
  {
    "title":"Measures",
    "submenu": [
      {
        "title":"file 4",
        "file":"file4"
      },
      {
        "title":"file 5",
        "file":"file5"
      },
      {
        "title":"file 6",
        "file":"file6"
      }
    ]
  }

]
